{"source": "canadawest.org", "teams": [["canadawest.org:team/z78yo6jcwew4e0xb", "Regina"], ["canadawest.org:team/w41s4fuy1ldg73vw", "Thompson Rivers"]], "sets": {"1": {"events": [{"point": "TRU", "server": "Michael Corrigan", "event": ["KILL", "Kyle Behiels", "Jakob Hamilton"]}, {"point": "TRU", "server": "Kyle Behiels", "event": ["KILL", "Anton Napolitano", "Jakob Hamilton"]}, {"point": "REG", "server": "Kyle Behiels", "event": ["KILL", "P.J. Seekings", "Michael Corrigan"]}, {"point": "TRU", "server": "P.J. Seekings", "event": ["KILL", "Anton Napolitano", "Jakob Hamilton"]}, {"point": "REG", "server": "Jakob Hamilton", "event": ["ATTACK_ERROR", "Daniel Eikland Rod"]}, {"point": "TRU", "server": "Cody Caldwell", "event": ["KILL", "Anton Napolitano", "Daniel Eikland Rod"]}, {"point": "REG", "server": "Charlie Bringloe", "event": ["KILL", "Dalton Wolfe", "Michael Corrigan"]}, {"point": "TRU", "server": "Matthew Aubrey", "event": ["SERVICE_ERROR"]}, {"point": "TRU", "server": "Jordan Foot", "event": ["KILL", "Anton Napolitano", "Jordan Foot"]}, {"point": "REG", "server": "Jordan Foot", "event": ["SERVICE_ERROR"]}, {"point": "TRU", "server": "Dalton Wolfe", "event": ["SERVICE_ERROR"]}, {"point": "REG", "server": "Anton Napolitano", "event": ["KILL", "Conal McAinsh", "Michael Corrigan"]}, {"point": "TRU", "server": "Conal McAinsh", "event": ["KILL", "Daniel Eikland Rod", "Jakob Hamilton"]}, {"point": "TRU", "server": "Daniel Eikland Rod", "event": ["KILL", "Charlie Bringloe", "Jakob Hamilton"]}, {"point": "REG", "server": "Daniel Eikland Rod", "event": ["KILL", "P.J. Seekings", "Michael Corrigan"]}, {"point": "TRU", "server": "Michael Corrigan", "event": ["KILL", "Charlie Bringloe", "Jakob Hamilton"]}, {"point": "REG", "server": "Kyle Behiels", "event": ["SERVICE_ERROR"]}, {"point": "TRU", "server": "P.J. Seekings", "event": ["KILL", "Jordan Foot", "Jakob Hamilton"]}, {"point": "TRU", "server": "Jakob Hamilton", "event": ["KILL", "Anton Napolitano", "Cole Keddie"]}, {"point": "REG", "server": "Jakob Hamilton", "event": ["KILL", "Matthew Aubrey", "Michael Corrigan"]}, {"point": "REG", "server": "Cody Caldwell", "event": ["SERVICE_ACE", "Cole Keddie"]}, {"point": "REG", "server": "Cody Caldwell", "event": ["ATTACK_ERROR", "Charlie Bringloe", ["Dalton Wolfe", "Conal McAinsh"]]}, {"point": "REG", "server": "Cody Caldwell", "event": ["KILL", "Matthew Aubrey", "Michael Corrigan"]}, {"point": "TRU", "server": "Cody Caldwell", "event": ["SERVICE_ERROR"]}, {"point": "REG", "server": "Charlie Bringloe", "event": ["SERVICE_ERROR"]}, {"point": "REG", "server": "Matthew Aubrey", "event": ["KILL", "Conal McAinsh"]}, {"point": "TRU", "server": "Matthew Aubrey", "event": ["SERVICE_ERROR"]}, {"point": "REG", "server": "Jordan Foot", "event": ["KILL", "Dalton Wolfe", "Michael Corrigan"]}, {"point": "TRU", "server": "Dalton Wolfe", "event": ["KILL", "Daniel Eikland Rod", "Jakob Hamilton"]}, {"point": "REG", "server": "Anton Napolitano", "event": ["KILL", "P.J. Seekings", "Michael Corrigan"]}, {"point": "REG", "server": "Conal McAinsh", "event": ["KILL", "P.J. Seekings", "Conal McAinsh"]}, {"point": "TRU", "server": "Conal McAinsh", "event": ["SERVICE_ERROR"]}, {"point": "TRU", "server": "Daniel Eikland Rod", "event": ["KILL", "Daniel Eikland Rod", "Jakob Hamilton"]}, {"point": "REG", "server": "Daniel Eikland Rod", "event": ["KILL", "P.J. Seekings", "Michael Corrigan", "Kyle Behiels"]}, {"point": "TRU", "server": "Michael Corrigan", "event": ["KILL", "Kyle Behiels", "Jakob Hamilton"]}, {"point": "TRU", "server": "Kyle Behiels", "event": ["KILL", "Charlie Bringloe", "Jakob Hamilton"]}, ["SUB", "REG subs: Taylor Towle."], {"point": "REG", "server": "Kyle Behiels", "event": ["KILL", "Matthew Aubrey", "Michael Corrigan"]}, {"point": "TRU", "server": "Taylor Towle", "event": ["ATTACK_ERROR", "Dalton Wolfe"]}, {"point": "TRU", "server": "Jakob Hamilton", "event": ["KILL", "Anton Napolitano", "Jakob Hamilton", "Matthew Aubrey"]}, ["TIMEOUT", "Timeout Regina."], {"point": "REG", "server": "Jakob Hamilton", "event": ["KILL", "Dalton Wolfe", "Michael Corrigan"]}, ["SUB", "REG subs: Dylan Smith."], {"point": "TRU", "server": "Dylan Smith", "event": ["KILL", "Anton Napolitano", "Jakob Hamilton"]}, ["SUB", "REG subs: Cody Caldwell."], ["SUB", "TRU subs: Isaac Smit."], {"point": "REG", "server": "Isaac Smit", "event": ["ATTACK_ERROR", "Daniel Eikland Rod"]}, ["TIMEOUT", "Timeout Thompson Rivers."], {"point": "REG", "server": "Matthew Aubrey", "event": ["ATTACK_ERROR", "Anton Napolitano"]}, {"point": "REG", "server": "Matthew Aubrey", "event": ["KILL", "Michael Corrigan", "Dryden Wall"]}, ["TIMEOUT", "Timeout Thompson Rivers."], {"point": "TRU", "server": "Matthew Aubrey", "event": ["SERVICE_ERROR"]}, {"point": "REG", "server": "Jordan Foot", "event": ["KILL", "Dalton Wolfe"]}, {"point": "TRU", "server": "Dalton Wolfe", "event": ["SERVICE_ERROR"]}, {"point": "REG", "server": "Anton Napolitano", "event": ["KILL", "Matthew Aubrey", "Michael Corrigan"]}, ["SUB", "REG subs: Noah Young; Brennan Goski."], {"point": "TRU", "server": "Noah Young", "event": ["KILL", "Anton Napolitano", "Isaac Smit"]}, ["SUB", "TRU subs: Charlie Bringloe."], ["SUB", "REG subs: Conal McAinsh; Michael Corrigan."], {"point": "TRU", "server": "Daniel Eikland Rod", "event": ["ATTACK_ERROR", "Cody Caldwell"]}], "starters": {"REG": ["P.J. Seekings", "Cody Caldwell", "Dalton Wolfe", "Matthew Aubrey", "Conal McAinsh", "Michael Corrigan", "Dryden Wall"], "TRU": ["Anton Napolitano", "Charlie Bringloe", "Daniel Eikland Rod", "Jakob Hamilton", "Jordan Foot", "Kyle Behiels", "Cole Keddie"]}}, "2": {"events": [{"point": "TRU", "server": "Jakob Hamilton", "event": ["ATTACK_ERROR", "P.J. Seekings"]}, {"point": "REG", "server": "Jakob Hamilton", "event": ["KILL", "P.J. Seekings", "Dryden Wall"]}, {"point": "TRU", "server": "Michael Corrigan", "event": ["KILL", "Daniel Eikland Rod", "Jakob Hamilton"]}, {"point": "REG", "server": "Charlie Bringloe", "event": ["SERVICE_ERROR"]}, {"point": "REG", "server": "P.J. Seekings", "event": ["SERVICE_ACE", "Cole Keddie"]}, {"point": "TRU", "server": "P.J. Seekings", "event": ["SERVICE_ERROR"]}, {"point": "REG", "server": "Jordan Foot", "event": ["KILL", "Dalton Wolfe", "Michael Corrigan"]}, {"point": "TRU", "server": "Conal McAinsh", "event": ["KILL", "Kyle Behiels", "Jakob Hamilton"]}, {"point": "TRU", "server": "Anton Napolitano", "event": ["ATTACK_ERROR", "Cody Caldwell"]}, {"point": "TRU", "server": "Anton Napolitano", "event": ["KILL", "Daniel Eikland Rod"]}, {"point": "TRU", "server": "Anton Napolitano", "event": ["KILL", "Anton Napolitano", "Cole Keddie"]}, {"point": "TRU", "server": "Anton Napolitano", "event": ["SERVICE_ACE", "Dalton Wolfe"]}, ["TIMEOUT", "Timeout Regina."], {"point": "REG", "server": "Anton Napolitano", "event": ["KILL", "Cody Caldwell", "Michael Corrigan"]}, {"point": "TRU", "server": "Matthew Aubrey", "event": ["KILL", "Kyle Behiels", "Jakob Hamilton"]}, {"point": "TRU", "server": "Daniel Eikland Rod", "event": ["SERVICE_ACE", "P.J. Seekings"]}, {"point": "REG", "server": "Daniel Eikland Rod", "event": ["KILL", "Matthew Aubrey", "P.J. Seekings"]}, {"point": "TRU", "server": "Dalton Wolfe", "event": ["KILL", "Charlie Bringloe", "Jakob Hamilton"]}, {"point": "REG", "server": "Kyle Behiels", "event": ["KILL", "P.J. Seekings", "Michael Corrigan"]}, {"point": "TRU", "server": "Cody Caldwell", "event": ["SERVICE_ERROR"]}, {"point": "TRU", "server": "Jakob Hamilton", "event": ["ATTACK_ERROR", "Matthew Aubrey", ["Charlie Bringloe", "Jordan Foot"]]}, {"point": "REG", "server": "Jakob Hamilton", "event": ["KILL", "P.J. Seekings", "Michael Corrigan"]}, {"point": "TRU", "server": "Michael Corrigan", "event": ["SERVICE_ERROR"]}, {"point": "TRU", "server": "Charlie Bringloe", "event": ["BAD_SET", "Michael Corrigan"]}, {"point": "REG", "server": "Charlie Bringloe", "event": ["SERVICE_ERROR"]}, {"point": "TRU", "server": "P.J. Seekings", "event": ["KILL", "Daniel Eikland Rod", "Jordan Foot"]}, {"point": "REG", "server": "Jordan Foot", "event": ["KILL", "Dalton Wolfe", "Michael Corrigan"]}, {"point": "REG", "server": "Conal McAinsh", "event": ["KILL", "Cody Caldwell"]}, {"point": "TRU", "server": "Conal McAinsh", "event": ["KILL", "Daniel Eikland Rod", "Jakob Hamilton"]}, {"point": "TRU", "server": "Anton Napolitano", "event": ["KILL", "Daniel Eikland Rod", "Cole Keddie"]}, {"point": "REG", "server": "Anton Napolitano", "event": ["KILL", "Cody Caldwell", "Michael Corrigan"]}, {"point": "REG", "server": "Matthew Aubrey", "event": ["KILL", "Dalton Wolfe", "Michael Corrigan"]}, {"point": "TRU", "server": "Matthew Aubrey", "event": ["SERVICE_ERROR"]}, {"point": "TRU", "server": "Daniel Eikland Rod", "event": ["ATTACK_ERROR", "Dalton Wolfe", ["Jakob Hamilton", "Kyle Behiels"]]}, ["TIMEOUT", "Timeout Regina."], {"point": "REG", "server": "Daniel Eikland Rod", "event": ["KILL", "Matthew Aubrey", "Michael Corrigan"]}, {"point": "TRU", "server": "Dalton Wolfe", "event": ["SERVICE_ERROR"]}, {"point": "REG", "server": "Kyle Behiels", "event": ["ATTACK_ERROR", "Charlie Bringloe"]}, ["SUB", "REG subs: Dylan Smith."], {"point": "TRU", "server": "Dylan Smith", "event": ["KILL", "Charlie Bringloe", "Jakob Hamilton"]}, {"point": "REG", "server": "Jakob Hamilton", "event": ["KILL", "Matthew Aubrey", "Michael Corrigan", "Charlie Bringloe"]}, {"point": "TRU", "server": "Michael Corrigan", "event": ["KILL", "Charlie Bringloe", "Jakob Hamilton"]}, ["SUB", "TRU subs: Isaac Smit."], {"point": "REG", "server": "Isaac Smit", "event": ["KILL", "P.J. Seekings", "Michael Corrigan"]}, {"point": "TRU", "server": "P.J. Seekings", "event": ["KILL", "Daniel Eikland Rod", "Jakob Hamilton", "Matthew Aubrey"]}, ["SUB", "REG subs: Taylor Towle."], {"point": "REG", "server": "Jordan Foot", "event": ["KILL", "Conal McAinsh", "Michael Corrigan"]}, ["SUB", "REG subs: Noah Young; Cody Caldwell."], {"point": "TRU", "server": "Noah Young", "event": ["KILL", "Kyle Behiels", "Jakob Hamilton"]}], "starters": {"REG": ["Michael Corrigan", "Dalton Wolfe", "Conal McAinsh", "P.J. Seekings", "Matthew Aubrey", "Cody Caldwell", "Dryden Wall"], "TRU": ["Jakob Hamilton", "Daniel Eikland Rod", "Anton Napolitano", "Charlie Bringloe", "Jordan Foot", "Kyle Behiels", "Cole Keddie"]}}, "3": {"events": [{"point": "TRU", "server": "Michael Corrigan", "event": ["SERVICE_ERROR"]}, {"point": "REG", "server": "Jordan Foot", "event": ["KILL", "P.J. Seekings", "Michael Corrigan"]}, {"point": "REG", "server": "P.J. Seekings", "event": ["SERVICE_ACE", "Charlie Bringloe"]}, {"point": "TRU", "server": "P.J. Seekings", "event": ["SERVICE_ERROR"]}, {"point": "REG", "server": "Anton Napolitano", "event": ["KILL", "Cody Caldwell", "Michael Corrigan"]}, {"point": "TRU", "server": "Cody Caldwell", "event": ["ATTACK_ERROR", "Dalton Wolfe"]}, {"point": "REG", "server": "Daniel Eikland Rod", "event": ["KILL", "Matthew Aubrey", "Michael Corrigan"]}, {"point": "TRU", "server": "Matthew Aubrey", "event": ["SERVICE_ERROR"]}, {"point": "TRU", "server": "Kyle Behiels", "event": ["ATTACK_ERROR", "Matthew Aubrey"]}, {"point": "REG", "server": "Kyle Behiels", "event": ["KILL", "Dalton Wolfe", "Michael Corrigan"]}, {"point": "REG", "server": "Dalton Wolfe", "event": ["ATTACK_ERROR", "Charlie Bringloe", ["Michael Corrigan", "Conal McAinsh"]]}, {"point": "TRU", "server": "Dalton Wolfe", "event": ["KILL", "Charlie Bringloe", "Jakob Hamilton"]}, {"point": "TRU", "server": "Jakob Hamilton", "event": ["KILL", "Charlie Bringloe", "Jakob Hamilton"]}, {"point": "REG", "server": "Jakob Hamilton", "event": ["KILL", "Matthew Aubrey", "Michael Corrigan"]}, {"point": "TRU", "server": "Conal McAinsh", "event": ["KILL", "Anton Napolitano", "Jakob Hamilton"]}, {"point": "REG", "server": "Charlie Bringloe", "event": ["SERVICE_ERROR"]}, {"point": "TRU", "server": "Michael Corrigan", "event": ["KILL", "Anton Napolitano", "Jakob Hamilton"]}, {"point": "REG", "server": "Jordan Foot", "event": ["KILL", "Cody Caldwell", "Michael Corrigan"]}, {"point": "TRU", "server": "P.J. Seekings", "event": ["SERVICE_ERROR"]}, {"point": "REG", "server": "Anton Napolitano", "event": ["SERVICE_ERROR"]}, {"point": "REG", "server": "Cody Caldwell", "event": ["BHE", "Jakob Hamilton"]}, {"point": "TRU", "server": "Cody Caldwell", "event": ["SERVICE_ERROR"]}, {"point": "REG", "server": "Daniel Eikland Rod", "event": ["KILL", "Dalton Wolfe", "Michael Corrigan"]}, {"point": "REG", "server": "Matthew Aubrey", "event": ["ATTACK_ERROR", "Daniel Eikland Rod"]}, {"point": "REG", "server": "Matthew Aubrey", "event": ["ATTACK_ERROR", "Kyle Behiels"]}, ["TIMEOUT", "Timeout Thompson Rivers."], {"point": "TRU", "server": "Matthew Aubrey", "event": ["KILL", "Charlie Bringloe", "Jakob Hamilton"]}, {"point": "REG", "server": "Kyle Behiels", "event": ["KILL", "Dalton Wolfe", "Michael Corrigan"]}, {"point": "REG", "server": "Dalton Wolfe", "event": ["ATTACK_ERROR", "Charlie Bringloe", ["Michael Corrigan", "Conal McAinsh"]]}, {"point": "TRU", "server": "Dalton Wolfe", "event": ["KILL", "Charlie Bringloe", "Jakob Hamilton"]}, {"point": "REG", "server": "Jakob Hamilton", "event": ["KILL", "Conal McAinsh", "Michael Corrigan"]}, {"point": "REG", "server": "Conal McAinsh", "event": ["ATTACK_ERROR", "Anton Napolitano"]}, ["TIMEOUT", "Timeout Thompson Rivers."], {"point": "TRU", "server": "Conal McAinsh", "event": ["KILL", "Anton Napolitano", "Jakob Hamilton"]}, ["SUB", "TRU subs: Isaac Smit."], {"point": "REG", "server": "Isaac Smit", "event": ["KILL", "P.J. Seekings", "Michael Corrigan"]}, {"point": "TRU", "server": "Michael Corrigan", "event": ["KILL", "Anton Napolitano", "Jakob Hamilton"]}, {"point": "REG", "server": "Jordan Foot", "event": ["KILL", "Matthew Aubrey", "Michael Corrigan"]}, {"point": "REG", "server": "P.J. Seekings", "event": ["ATTACK_ERROR", "Anton Napolitano", ["Cody Caldwell", "Dalton Wolfe"]]}, {"point": "REG", "server": "P.J. Seekings", "event": ["KILL", "Matthew Aubrey", "Michael Corrigan"]}, {"point": "TRU", "server": "P.J. Seekings", "event": ["SERVICE_ERROR"]}, ["SUB", "REG subs: Taylor Towle."], {"point": "TRU", "server": "Anton Napolitano", "event": ["SERVICE_ACE", "Dryden Wall"]}, {"point": "REG", "server": "Anton Napolitano", "event": ["KILL", "Matthew Aubrey", "Michael Corrigan", "Kyle Behiels"]}, ["SUB", "REG subs: Dylan Smith."], {"point": "REG", "server": "Dylan Smith", "event": ["ATTACK_ERROR", "Kyle Behiels"]}, {"point": "REG", "server": "Dylan Smith", "event": ["KILL", "Conal McAinsh", "Michael Corrigan"]}], "starters": {"REG": ["Cody Caldwell", "Matthew Aubrey", "P.J. Seekings", "Conal McAinsh", "Michael Corrigan", "Dalton Wolfe", "Dryden Wall"], "TRU": ["Charlie Bringloe", "Jordan Foot", "Anton Napolitano", "Daniel Eikland Rod", "Kyle Behiels", "Jakob Hamilton", "Cole Keddie"]}}, "4": {"events": [{"point": "REG", "server": "Jakob Hamilton", "event": ["ATTACK_ERROR", "Charlie Bringloe"]}, {"point": "REG", "server": "Cody Caldwell", "event": ["ATTACK_ERROR", "Anton Napolitano", ["Matthew Aubrey", "Conal McAinsh"]]}, {"point": "TRU", "server": "Cody Caldwell", "event": ["KILL", "Kyle Behiels", "Jakob Hamilton"]}, {"point": "REG", "server": "Charlie Bringloe", "event": ["KILL", "Matthew Aubrey", "Michael Corrigan"]}, {"point": "TRU", "server": "Matthew Aubrey", "event": ["KILL", "Daniel Eikland Rod", "Jakob Hamilton"]}, {"point": "REG", "server": "Kyle Behiels", "event": ["KILL", "Conal McAinsh", "Michael Corrigan"]}, {"point": "REG", "server": "Dalton Wolfe", "event": ["ATTACK_ERROR", "Daniel Eikland Rod"]}, {"point": "TRU", "server": "Dalton Wolfe", "event": ["KILL", "Daniel Eikland Rod", "Jordan Foot", "Conal McAinsh"]}, {"point": "REG", "server": "Anton Napolitano", "event": ["KILL", "Matthew Aubrey", "Michael Corrigan"]}, {"point": "REG", "server": "Conal McAinsh", "event": ["SERVICE_ACE", "Daniel Eikland Rod"]}, ["TIMEOUT", "Timeout Thompson Rivers."], ["SUB", "TRU subs: Randy Grundmann."], {"point": "TRU", "server": "Conal McAinsh", "event": ["KILL", "Randy Grundmann", "Jakob Hamilton"]}, {"point": "REG", "server": "Randy Grundmann", "event": ["SERVICE_ERROR"]}, {"point": "REG", "server": "Michael Corrigan", "event": ["ATTACK_ERROR", "Anton Napolitano"]}, {"point": "TRU", "server": "Michael Corrigan", "event": ["KILL", "Charlie Bringloe", "Jakob Hamilton"]}, {"point": "REG", "server": "Jordan Foot", "event": ["KILL", "P.J. Seekings", "Michael Corrigan"]}, {"point": "TRU", "server": "P.J. Seekings", "event": ["SERVICE_ERROR"]}, {"point": "TRU", "server": "Jakob Hamilton", "event": ["ATTACK_ERROR", "Dalton Wolfe", ["Anton Napolitano", "Kyle Behiels"]]}, {"point": "REG", "server": "Jakob Hamilton", "event": ["KILL", "Matthew Aubrey", "Michael Corrigan"]}, {"point": "REG", "server": "Cody Caldwell", "event": ["ATTACK_ERROR", "Anton Napolitano", ["Matthew Aubrey", "Conal McAinsh"]]}, {"point": "TRU", "server": "Cody Caldwell", "event": ["KILL", "Kyle Behiels", "Jakob Hamilton"]}, {"point": "TRU", "server": "Charlie Bringloe", "event": ["ATTACK_ERROR", "Dalton Wolfe", ["Kyle Behiels", "Anton Napolitano"]]}, {"point": "TRU", "server": "Charlie Bringloe", "event": ["KILL", "Randy Grundmann", "Jakob Hamilton"]}, {"point": "REG", "server": "Charlie Bringloe", "event": ["SERVICE_ERROR"]}, {"point": "TRU", "server": "Matthew Aubrey", "event": ["KILL", "Randy Grundmann", "Jakob Hamilton"]}, {"point": "TRU", "server": "Kyle Behiels", "event": ["SERVICE_ACE", "P.J. Seekings"]}, {"point": "TRU", "server": "Kyle Behiels", "event": ["ATTACK_ERROR", "Dalton Wolfe", ["Jordan Foot", "Anton Napolitano"]]}, {"point": "REG", "server": "Kyle Behiels", "event": ["KILL", "Matthew Aubrey", "Michael Corrigan"]}, {"point": "TRU", "server": "Dalton Wolfe", "event": ["KILL", "Randy Grundmann", "Jakob Hamilton"]}, {"point": "TRU", "server": "Anton Napolitano", "event": ["ATTACK_ERROR", "P.J. Seekings", ["Jakob Hamilton", "Jordan Foot"]]}, ["YELLOW_CARD", "???", "yellow card TRU #1"], {"point": "REG", "server": "Anton Napolitano", "event": ["SERVICE_ERROR"]}, {"point": "REG", "server": "Conal McAinsh", "event": ["KILL", "Michael Corrigan"]}, {"point": "TRU", "server": "Conal McAinsh", "event": ["KILL", "Randy Grundmann", "Jakob Hamilton"]}, {"point": "REG", "server": "Randy Grundmann", "event": ["KILL", "P.J. Seekings", "Michael Corrigan"]}, {"point": "TRU", "server": "Michael Corrigan", "event": ["KILL", "Jordan Foot", "Jakob Hamilton"]}, {"point": "REG", "server": "Jordan Foot", "event": ["SERVICE_ERROR"]}, {"point": "TRU", "server": "P.J. Seekings", "event": ["KILL", "Kyle Behiels", "Jakob Hamilton"]}, ["SUB", "REG subs: Taylor Towle."], {"point": "REG", "server": "Jakob Hamilton", "event": ["KILL", "Dalton Wolfe", "Michael Corrigan"]}, ["SUB", "REG subs: Dylan Smith."], {"point": "REG", "server": "Dylan Smith", "event": ["SERVICE_ACE", "Cole Keddie"]}, ["TIMEOUT", "Timeout Thompson Rivers."], {"point": "REG", "server": "Dylan Smith", "event": ["ATTACK_ERROR", "Anton Napolitano"]}, {"point": "TRU", "server": "Dylan Smith", "event": ["KILL", "Anton Napolitano", "Jakob Hamilton", "Matthew Aubrey"]}, ["SUB", "TRU subs: Isaac Smit."], {"point": "TRU", "server": "Isaac Smit", "event": ["SERVICE_ACE", "Dryden Wall"]}, {"point": "TRU", "server": "Isaac Smit", "event": ["ATTACK_ERROR", "Matthew Aubrey", ["Randy Grundmann", "Kyle Behiels"]]}, ["TIMEOUT", "Timeout Regina."], {"point": "TRU", "server": "Isaac Smit", "event": ["ATTACK_ERROR", "Matthew Aubrey"]}, {"point": "TRU", "server": "Isaac Smit", "event": ["KILL", "Randy Grundmann", "Jakob Hamilton"]}, ["TIMEOUT", "Timeout Regina."], {"point": "REG", "server": "Isaac Smit", "event": ["ATTACK_ERROR", "Anton Napolitano"]}, ["SUB", "REG subs: Brennan Goski."], {"point": "TRU", "server": "Matthew Aubrey", "event": ["KILL", "Randy Grundmann", "Jakob Hamilton"]}, ["SUB", "REG subs: Michael Corrigan."], {"point": "REG", "server": "Kyle Behiels", "event": ["KILL", "Dalton Wolfe", "Michael Corrigan"]}, ["SUB", "REG subs: P.J. Seekings."], {"point": "REG", "server": "Dalton Wolfe", "event": ["KILL", "P.J. Seekings", "Conal McAinsh"]}, {"point": "TRU", "server": "Dalton Wolfe", "event": ["KILL", "Randy Grundmann", "Jakob Hamilton"]}, {"point": "REG", "server": "Anton Napolitano", "event": ["KILL", "P.J. Seekings", "Dryden Wall"]}, ["SUB", "REG subs: Noah Young."], {"point": "REG", "server": "Conal McAinsh", "event": ["ATTACK_ERROR", "Randy Grundmann", ["Cody Caldwell", "Michael Corrigan"]]}, {"point": "REG", "server": "Conal McAinsh", "event": ["ATTACK_ERROR", "Randy Grundmann"]}], "starters": {"REG": ["Conal McAinsh", "Dalton Wolfe", "Michael Corrigan", "P.J. Seekings", "Matthew Aubrey", "Cody Caldwell", "Dryden Wall"], "TRU": ["Jakob Hamilton", "Jordan Foot", "Daniel Eikland Rod", "Anton Napolitano", "Charlie Bringloe", "Kyle Behiels", "Cole Keddie"]}}, "5": {"events": [{"point": "TRU", "server": "Jakob Hamilton", "event": ["ATTACK_ERROR", "Dalton Wolfe"]}, {"point": "TRU", "server": "Jakob Hamilton", "event": ["KILL", "Charlie Bringloe"]}, {"point": "REG", "server": "Jakob Hamilton", "event": ["KILL", "Dalton Wolfe", "Michael Corrigan"]}, {"point": "TRU", "server": "Cody Caldwell", "event": ["KILL", "Charlie Bringloe", "Jakob Hamilton"]}, {"point": "REG", "server": "Charlie Bringloe", "event": ["BHE", "Charlie Bringloe"]}, {"point": "REG", "server": "Matthew Aubrey", "event": ["KILL", "Dalton Wolfe", "Michael Corrigan", "Anton Napolitano"]}, {"point": "TRU", "server": "Matthew Aubrey", "event": ["KILL", "Randy Grundmann", "Jakob Hamilton"]}, {"point": "REG", "server": "Kyle Behiels", "event": ["KILL", "Dalton Wolfe", "Michael Corrigan"]}, {"point": "REG", "server": "Dalton Wolfe", "event": ["ATTACK_ERROR", "Jordan Foot", ["Conal McAinsh"]]}, {"point": "TRU", "server": "Dalton Wolfe", "event": ["KILL", "Randy Grundmann", "Jakob Hamilton"]}, {"point": "REG", "server": "Anton Napolitano", "event": ["KILL", "Matthew Aubrey", "Michael Corrigan"]}, {"point": "TRU", "server": "Conal McAinsh", "event": ["ATTACK_ERROR", "Matthew Aubrey", ["Jordan Foot", "Randy Grundmann"]]}, {"point": "REG", "server": "Randy Grundmann", "event": ["SERVICE_ERROR"]}, {"point": "TRU", "server": "Michael Corrigan", "event": ["KILL", "Anton Napolitano", "Jakob Hamilton"]}, {"point": "TRU", "server": "Jordan Foot", "event": ["SERVICE_ACE", "P.J. Seekings"]}, {"point": "TRU", "server": "Jordan Foot", "event": ["SERVICE_ACE", "Cody Caldwell"]}, ["TIMEOUT", "Timeout Regina."], {"point": "REG", "server": "Jordan Foot", "event": ["KILL", "Cody Caldwell", "Michael Corrigan"]}, {"point": "REG", "server": "P.J. Seekings", "event": ["KILL", "Dalton Wolfe", "Michael Corrigan"]}, {"point": "REG", "server": "P.J. Seekings", "event": ["ATTACK_ERROR", "Charlie Bringloe"]}, ["TIMEOUT", "Timeout Thompson Rivers."], {"point": "TRU", "server": "P.J. Seekings", "event": ["KILL", "Charlie Bringloe", "Jakob Hamilton"]}, ["SUB", "REG subs: Taylor Towle."], {"point": "TRU", "server": "Jakob Hamilton", "event": ["KILL", "Charlie Bringloe", "Jakob Hamilton"]}, {"point": "TRU", "server": "Jakob Hamilton", "event": ["KILL", "Anton Napolitano", "Cole Keddie"]}, ["TIMEOUT", "Timeout Regina."], {"point": "TRU", "server": "Jakob Hamilton", "event": ["KILL", "Charlie Bringloe"]}, {"point": "REG", "server": "Jakob Hamilton", "event": ["KILL", "Michael Corrigan"]}, ["SUB", "REG subs: Dylan Smith."], {"point": "REG", "server": "Dylan Smith", "event": ["ATTACK_ERROR", "Anton Napolitano"]}, {"point": "TRU", "server": "Dylan Smith", "event": ["KILL", "Kyle Behiels", "Jakob Hamilton"]}, ["SUB", "TRU subs: Isaac Smit."], {"point": "REG", "server": "Isaac Smit", "event": ["ATTACK_ERROR", "Anton Napolitano"]}, ["SUB", "REG subs: Brennan Goski."], {"point": "TRU", "server": "Matthew Aubrey", "event": ["KILL", "Randy Grundmann", "Jakob Hamilton"]}], "starters": {"REG": ["Michael Corrigan", "P.J. Seekings", "Cody Caldwell", "Dalton Wolfe", "Matthew Aubrey", "Conal McAinsh", "Dryden Wall"], "TRU": ["Anton Napolitano", "Charlie Bringloe", "Kyle Behiels", "Randy Grundmann", "Jordan Foot", "Jakob Hamilton", "Cole Keddie"]}}}, "id": "canadawest.org:game/20170128_xhfr", "date": "2017-01-28"}