{"id": "canadawest.org:game/20170113_9w9e", "teams": {"UBC Okanagan": [["canadawest.org:player/a65syreuli37qd1h", "Kyle Hinchey", {"TA": 30, "DIGS": 3}], ["canadawest.org:player/elocks886tfyrr2h", "Lars Bornemann", {"TA": 28, "DIGS": 5}], ["canadawest.org:player/21ebv2a2c61yklnq", "Alex Swiatlowski", {"TA": 14, "DIGS": 0}], ["canadawest.org:player/c7646eoodigkku83", "Devon Cote", {"TA": 14, "DIGS": 2}], ["canadawest.org:player/q6xsziwhi8qgf5vr", "Joshua Harvey", {"TA": 13, "DIGS": 0}], ["canadawest.org:player/nxwm0do1gloych3y", "Ethan Freund", {"TA": 4, "DIGS": 4}], ["canadawest.org:player/hnpgswhluyx98c46", "Eli Risso", {"TA": 0, "DIGS": 6}], ["canadawest.org:player/loqddn1cmvluhh25", "Micah Brown", {"TA": 0, "DIGS": 0}], ["canadawest.org:player/flwuvydmda404knf", "Luke Harvey", {"TA": 2, "DIGS": 0}], ["canadawest.org:player/0gj7k98e0djyobri", "Adam Kern", {"TA": 1, "DIGS": 0}], ["canadawest.org:player/9ngldsg63rqt3zw0", "Adam Schwarz", {"TA": 0, "DIGS": 0}]], "Winnipeg": [["canadawest.org:player/fyrw2152trw2hwn8", "Brendan Thielmann", {"TA": 20, "DIGS": 4}], ["canadawest.org:player/fnt4fh6mt5da8bck", "Casey Schouten", {"TA": 19, "DIGS": 4}], ["canadawest.org:player/ce8mtrkuh3whis8q", "Mikael Clegg", {"TA": 0, "DIGS": 6}], ["canadawest.org:player/ofhppsvlm5yytwl7", "Garrett Jones", {"TA": 14, "DIGS": 0}], ["canadawest.org:player/mf4jpztbc7n46opu", "Ethan Duncan", {"TA": 7, "DIGS": 2}], ["canadawest.org:player/jymwy5gcg9r5ll3l", "Taylor Howe", {"TA": 18, "DIGS": 4}], ["canadawest.org:player/fhgebjqscdnwgn8u", "Bryce Edwards", {"TA": 0, "DIGS": 2}], ["canadawest.org:player/3lf0mst6cdn5al2s", "Daniel Thiessen", {"TA": 1, "DIGS": 0}], ["canadawest.org:player/7k9zm3qj6xuk6rsf", "Nolan Parrington", {"TA": 1, "DIGS": 1}], ["canadawest.org:player/7cmjw7jj8boe8j0d", "Logan Brennan", {"TA": 0, "DIGS": 4}], ["canadawest.org:player/b8czli2u5xk9e767", "Jaden Prive", {"TA": 2, "DIGS": 0}]]}, "ta_per_set": {"UBC Okanagan": [26, 30, 22, 28], "Winnipeg": [18, 24, 18, 22]}, "source": "canadawest.org"}