{"sets": {"1": {"starters": {"REG": ["P.J. Seekings", "Cody Caldwell", "Matthew Aubrey", "Dalton Wolfe", "Conal McAinsh", "Michael Corrigan", "Dryden Wall"], "BRNM": ["Reece Dixon", "James Weir", "Elliott Viles", "Roy Ching", "Matt Powell", "Mason Metcalf", "Jeremy Davies"]}, "events": [{"event": ["KILL", "Conal McAinsh", "P.J. Seekings"], "server": "Reece Dixon", "point": "REG"}, {"event": ["SERVICE_ERROR"], "server": "Conal McAinsh", "point": "BRNM"}, {"event": ["KILL", "Dalton Wolfe", "Michael Corrigan"], "server": "Elliott Viles", "point": "REG"}, {"event": ["KILL", "Roy Ching", "Jeremy Davies"], "server": "Matthew Aubrey", "point": "BRNM"}, {"event": ["ATTACK_ERROR", "Matthew Aubrey"], "server": "Mason Metcalf", "point": "BRNM"}, {"event": ["ATTACK_ERROR", "Matthew Aubrey", ["James Weir", "Roy Ching", "Matt Powell"]], "server": "Mason Metcalf", "point": "BRNM"}, {"event": ["ATTACK_ERROR", "Dalton Wolfe", ["Matt Powell", "James Weir"]], "server": "Mason Metcalf", "point": "BRNM"}, {"event": ["KILL", "Dalton Wolfe", "Michael Corrigan"], "server": "Mason Metcalf", "point": "REG"}, {"event": ["ATTACK_ERROR", "Roy Ching"], "server": "Dalton Wolfe", "point": "REG"}, {"event": ["KILL", "James Weir", "Reece Dixon"], "server": "Dalton Wolfe", "point": "BRNM"}, {"event": ["KILL", "Cody Caldwell", "Michael Corrigan"], "server": "Matt Powell", "point": "REG"}, {"event": ["ATTACK_ERROR", "Roy Ching", ["Michael Corrigan"]], "server": "Cody Caldwell", "point": "REG"}, {"event": ["KILL", "James Weir", "Reece Dixon"], "server": "Cody Caldwell", "point": "BRNM"}, {"event": ["SERVICE_ERROR"], "server": "Roy Ching", "point": "REG"}, {"event": ["KILL", "Elliott Viles", "Reece Dixon"], "server": "Michael Corrigan", "point": "BRNM"}, {"event": ["ATTACK_ERROR", "Matthew Aubrey"], "server": "James Weir", "point": "BRNM"}, {"event": ["KILL", "Conal McAinsh", "Michael Corrigan"], "server": "James Weir", "point": "REG"}, {"event": ["ATTACK_ERROR", "Mason Metcalf", ["Conal McAinsh", "Matthew Aubrey"]], "server": "P.J. Seekings", "point": "REG"}, {"event": ["SERVICE_ERROR"], "server": "P.J. Seekings", "point": "BRNM"}, {"event": ["KILL", "Elliott Viles"], "server": "Reece Dixon", "point": "BRNM"}, {"event": ["KILL", "Matthew Aubrey", "Michael Corrigan"], "server": "Reece Dixon", "point": "REG"}, {"event": ["SERVICE_ERROR"], "server": "Conal McAinsh", "point": "BRNM"}, {"event": ["KILL", "Roy Ching", "Reece Dixon"], "server": "Elliott Viles", "point": "BRNM"}, {"event": ["KILL", "Matthew Aubrey", "Michael Corrigan"], "server": "Elliott Viles", "point": "REG"}, {"event": ["SERVICE_ERROR"], "server": "Matthew Aubrey", "point": "BRNM"}, {"event": ["KILL", "Matthew Aubrey", "Michael Corrigan"], "server": "Mason Metcalf", "point": "REG"}, {"event": ["KILL", "Matt Powell", "Reece Dixon"], "server": "Dalton Wolfe", "point": "BRNM"}, {"event": ["ATTACK_ERROR", "Cody Caldwell"], "server": "Matt Powell", "point": "BRNM"}, {"event": ["KILL", "James Weir", "Reece Dixon"], "server": "Matt Powell", "point": "BRNM"}, {"event": ["ATTACK_ERROR", "P.J. Seekings"], "server": "Matt Powell", "point": "BRNM"}, ["SUB", "REG subs: Noah Young; Brennan Goski."], {"event": ["BAD_SET", "Brennan Goski"], "server": "Matt Powell", "point": "BRNM"}, ["TIMEOUT", "Timeout Regina."], {"event": ["ATTACK_ERROR", "P.J. Seekings", ["Roy Ching", "James Weir"]], "server": "Matt Powell", "point": "BRNM"}, ["TIMEOUT", "Timeout Regina."], {"event": ["SERVICE_ACE", "Dryden Wall"], "server": "Matt Powell", "point": "BRNM"}, ["SUB", "REG subs: Taylor Towle; Matthew Aubrey; Michael Corrigan."], {"event": ["KILL", "Cody Caldwell", "Michael Corrigan"], "server": "Matt Powell", "point": "REG"}, {"event": ["ATTACK_ERROR", "James Weir"], "server": "Cody Caldwell", "point": "REG"}, {"event": ["ATTACK_ERROR", "Roy Ching", ["Conal McAinsh", "Michael Corrigan", "Taylor Towle"]], "server": "Cody Caldwell", "point": "REG"}, {"event": ["SERVICE_ERROR"], "server": "Cody Caldwell", "point": "BRNM"}, {"event": ["ATTACK_ERROR", "Conal McAinsh", ["Elliott Viles", "James Weir"]], "server": "Roy Ching", "point": "BRNM"}, {"event": ["KILL", "Michael Corrigan"], "server": "Roy Ching", "point": "REG"}, {"event": ["ATTACK_ERROR", "Elliott Viles"], "server": "Michael Corrigan", "point": "REG"}, {"event": ["ATTACK_ERROR", "Matt Powell"], "server": "Michael Corrigan", "point": "REG"}, {"event": ["KILL", "James Weir", "Reece Dixon"], "server": "Michael Corrigan", "point": "BRNM"}, {"event": ["ATTACK_ERROR", "Matthew Aubrey"], "server": "James Weir", "point": "BRNM"}]}, "2": {"starters": {"REG": ["Conal McAinsh", "Cody Caldwell", "Taylor Towle", "Dryden Wall", "Matthew Aubrey", "Michael Corrigan", "Dalton Wolfe"], "BRNM": ["Reece Dixon", "Elliott Viles", "Mason Metcalf", "Roy Ching", "James Weir", "Matt Powell", "Jeremy Davies"]}, "events": [{"event": ["SERVICE_ACE", "Elliott Viles"], "server": "Michael Corrigan", "point": "REG"}, {"event": ["ATTACK_ERROR", "Taylor Towle"], "server": "Michael Corrigan", "point": "BRNM"}, {"event": ["ATTACK_ERROR", "Taylor Towle"], "server": "Reece Dixon", "point": "BRNM"}, {"event": ["KILL", "Taylor Towle", "Michael Corrigan"], "server": "Reece Dixon", "point": "REG"}, {"event": ["SERVICE_ERROR"], "server": "Taylor Towle", "point": "BRNM"}, {"event": ["ATTACK_ERROR", "Matt Powell", ["Dalton Wolfe", "Conal McAinsh"]], "server": "Elliott Viles", "point": "REG"}, {"event": ["ATTACK_ERROR", "Matt Powell"], "server": "Conal McAinsh", "point": "REG"}, {"event": ["KILL", "Roy Ching", "Jeremy Davies"], "server": "Conal McAinsh", "point": "BRNM"}, {"event": ["KILL", "Matthew Aubrey", "Michael Corrigan"], "server": "Mason Metcalf", "point": "REG"}, {"event": ["KILL", "Roy Ching", "Reece Dixon"], "server": "Matthew Aubrey", "point": "BRNM"}, {"event": ["ATTACK_ERROR", "Roy Ching"], "server": "Matt Powell", "point": "REG"}, {"event": ["KILL", "Matt Powell", "Reece Dixon"], "server": "Dalton Wolfe", "point": "BRNM"}, {"event": ["ATTACK_ERROR", "Taylor Towle"], "server": "Roy Ching", "point": "BRNM"}, {"event": ["KILL", "Cody Caldwell", "Michael Corrigan"], "server": "Roy Ching", "point": "REG"}, {"event": ["KILL", "Roy Ching", "Reece Dixon"], "server": "Cody Caldwell", "point": "BRNM"}, {"event": ["KILL", "Taylor Towle", "Michael Corrigan"], "server": "James Weir", "point": "REG"}, {"event": ["KILL", "Elliott Viles", "Reece Dixon"], "server": "Michael Corrigan", "point": "BRNM"}, {"event": ["KILL", "Matt Powell", "Reece Dixon"], "server": "Reece Dixon", "point": "BRNM"}, {"event": ["ATTACK_ERROR", "Taylor Towle", ["Mason Metcalf", "Elliott Viles"]], "server": "Reece Dixon", "point": "BRNM"}, ["TIMEOUT", "Timeout Regina."], {"event": ["ATTACK_ERROR", "Taylor Towle"], "server": "Reece Dixon", "point": "BRNM"}, {"event": ["ATTACK_ERROR", "Matthew Aubrey"], "server": "Reece Dixon", "point": "BRNM"}, {"event": ["ATTACK_ERROR", "Taylor Towle"], "server": "Reece Dixon", "point": "BRNM"}, ["SUB", "REG subs: Brennan Goski."], {"event": ["KILL", "Mason Metcalf", "Reece Dixon"], "server": "Reece Dixon", "point": "BRNM"}, {"event": ["SERVICE_ERROR"], "server": "Reece Dixon", "point": "REG"}, {"event": ["KILL", "Matthew Aubrey", "Michael Corrigan"], "server": "Brennan Goski", "point": "REG"}, {"event": ["ATTACK_ERROR", "Dalton Wolfe"], "server": "Brennan Goski", "point": "BRNM"}, {"event": ["SERVICE_ACE", "Dryden Wall"], "server": "Elliott Viles", "point": "BRNM"}, {"event": ["ATTACK_ERROR", "Conal McAinsh"], "server": "Elliott Viles", "point": "BRNM"}, ["SUB", "REG subs: Taylor Towle."], {"event": ["SERVICE_ACE", "Taylor Towle"], "server": "Elliott Viles", "point": "BRNM"}, {"event": ["KILL", "Taylor Towle", "Michael Corrigan"], "server": "Elliott Viles", "point": "REG"}, ["SUB", "REG subs: Dylan Smith."], {"event": ["KILL", "Mason Metcalf", "Reece Dixon"], "server": "Dylan Smith", "point": "BRNM"}, ["SUB", "BRNM subs: Daven Pascal."], {"event": ["KILL", "Matthew Aubrey", "Dryden Wall"], "server": "Mason Metcalf", "point": "REG"}, {"event": ["ATTACK_ERROR", "Matt Powell"], "server": "Matthew Aubrey", "point": "REG"}, {"event": ["KILL", "Michael Corrigan"], "server": "Matthew Aubrey", "point": "REG"}, {"event": ["ATTACK_ERROR", "Dalton Wolfe", ["Daven Pascal", "Matt Powell"]], "server": "Matthew Aubrey", "point": "BRNM"}, {"event": ["KILL", "Matt Powell", "Reece Dixon"], "server": "Matt Powell", "point": "BRNM"}, {"event": ["SERVICE_ERROR"], "server": "Matt Powell", "point": "REG"}, {"event": ["ATTACK_ERROR", "Daven Pascal"], "server": "Dalton Wolfe", "point": "REG"}, {"event": ["ATTACK_ERROR", "Matthew Aubrey"], "server": "Dalton Wolfe", "point": "BRNM"}, {"event": ["KILL", "Daven Pascal", "Reece Dixon"], "server": "Roy Ching", "point": "BRNM"}, {"event": ["KILL", "Taylor Towle", "Matthew Aubrey"], "server": "Roy Ching", "point": "REG"}, ["SUB", "REG subs: Conal McAinsh."], {"event": ["ATTACK_ERROR", "Roy Ching"], "server": "Cody Caldwell", "point": "REG"}, {"event": ["SERVICE_ERROR"], "server": "Cody Caldwell", "point": "BRNM"}]}, "3": {"starters": {"REG": ["Matthew Aubrey", "Taylor Towle", "Conal McAinsh", "Dalton Wolfe", "Cody Caldwell", "Dryden Wall", "Michael Corrigan"], "BRNM": ["Mason Metcalf", "Elliott Viles", "Matt Powell", "Reece Dixon", "Roy Ching", "James Weir", "Jeremy Davies"]}, "events": [{"event": ["KILL", "Elliott Viles", "Mason Metcalf"], "server": "Reece Dixon", "point": "BRNM"}, {"event": ["SERVICE_ERROR"], "server": "Reece Dixon", "point": "REG"}, {"event": ["SERVICE_ERROR"], "server": "Conal McAinsh", "point": "BRNM"}, {"event": ["SERVICE_ACE", "Dalton Wolfe"], "server": "Elliott Viles", "point": "BRNM"}, {"event": ["ATTACK_ERROR", "Matt Powell"], "server": "Elliott Viles", "point": "REG"}, {"event": ["ATTACK_ERROR", "Matt Powell", ["Dalton Wolfe", "Cody Caldwell"]], "server": "Matthew Aubrey", "point": "REG"}, {"event": ["KILL", "Mason Metcalf", "Reece Dixon"], "server": "Matthew Aubrey", "point": "BRNM"}, {"event": ["ATTACK_ERROR", "Dalton Wolfe"], "server": "Mason Metcalf", "point": "BRNM"}, {"event": ["ATTACK_ERROR", "Roy Ching", ["Michael Corrigan", "Matthew Aubrey"]], "server": "Mason Metcalf", "point": "REG"}, {"event": ["KILL", "Matthew Aubrey", "Dryden Wall"], "server": "Dalton Wolfe", "point": "REG"}, {"event": ["KILL", "Matt Powell"], "server": "Dalton Wolfe", "point": "BRNM"}, ["SUB", "BRNM subs: Seth Friesen."], {"event": ["SERVICE_ACE", "Dalton Wolfe"], "server": "Seth Friesen", "point": "BRNM"}, {"event": ["ATTACK_ERROR", "Cody Caldwell"], "server": "Seth Friesen", "point": "BRNM"}, {"event": ["KILL", "Taylor Towle", "Michael Corrigan"], "server": "Seth Friesen", "point": "REG"}, {"event": ["KILL", "Reece Dixon", "Elliott Viles"], "server": "Cody Caldwell", "point": "BRNM"}, {"event": ["SERVICE_ERROR"], "server": "Roy Ching", "point": "REG"}, {"event": ["KILL", "Reece Dixon", "Jeremy Davies"], "server": "Michael Corrigan", "point": "BRNM"}, {"event": ["ATTACK_ERROR", "Conal McAinsh"], "server": "James Weir", "point": "BRNM"}, {"event": ["KILL", "Elliott Viles", "Reece Dixon"], "server": "James Weir", "point": "BRNM"}, {"event": ["ATTACK_ERROR", "Taylor Towle"], "server": "James Weir", "point": "BRNM"}, {"event": ["SERVICE_ERROR"], "server": "James Weir", "point": "REG"}, {"event": ["KILL", "Elliott Viles", "Reece Dixon"], "server": "Taylor Towle", "point": "BRNM"}, {"event": ["KILL", "Matthew Aubrey", "Conal McAinsh"], "server": "Reece Dixon", "point": "REG"}, {"event": ["KILL", "Mason Metcalf", "Reece Dixon"], "server": "Conal McAinsh", "point": "BRNM"}, {"event": ["ATTACK_ERROR", "Dalton Wolfe"], "server": "Elliott Viles", "point": "BRNM"}, {"event": ["KILL", "Dalton Wolfe", "Michael Corrigan"], "server": "Elliott Viles", "point": "REG"}, {"event": ["SERVICE_ERROR"], "server": "Matthew Aubrey", "point": "BRNM"}, {"event": ["SERVICE_ERROR"], "server": "Mason Metcalf", "point": "REG"}, ["SUB", "BRNM subs: Brady Nault."], {"event": ["KILL", "Seth Friesen", "Reece Dixon"], "server": "Dalton Wolfe", "point": "BRNM"}, {"event": ["KILL", "James Weir", "Reece Dixon"], "server": "Seth Friesen", "point": "BRNM"}, {"event": ["SERVICE_ERROR"], "server": "Seth Friesen", "point": "REG"}, {"event": ["KILL", "Brady Nault", "Jeremy Davies"], "server": "Cody Caldwell", "point": "BRNM"}, {"event": ["SERVICE_ACE", "Dalton Wolfe"], "server": "Brady Nault", "point": "BRNM"}, ["TIMEOUT", "Timeout Regina."], {"event": ["KILL", "Matthew Aubrey", "Michael Corrigan"], "server": "Brady Nault", "point": "REG"}, {"event": ["KILL", "Elliott Viles", "Reece Dixon"], "server": "Michael Corrigan", "point": "BRNM"}, ["SUB", "BRNM subs: Daven Pascal."], {"event": ["KILL", "Matthew Aubrey", "Michael Corrigan"], "server": "James Weir", "point": "REG"}, {"event": ["ATTACK_ERROR", "Seth Friesen"], "server": "Taylor Towle", "point": "REG"}, {"event": ["ATTACK_ERROR", "Matthew Aubrey"], "server": "Taylor Towle", "point": "BRNM"}, {"event": ["KILL", "Seth Friesen", "Reece Dixon"], "server": "Reece Dixon", "point": "BRNM"}, {"event": ["SERVICE_ERROR"], "server": "Reece Dixon", "point": "REG"}, {"event": ["KILL", "Matthew Aubrey", "Michael Corrigan"], "server": "Conal McAinsh", "point": "REG"}, {"event": ["ATTACK_ERROR", "Matthew Aubrey", ["Seth Friesen", "Daven Pascal"]], "server": "Conal McAinsh", "point": "BRNM"}]}}, "date": "2017-01-12", "teams": [["canadawest.org:team/z78yo6jcwew4e0xb", "Regina"], ["canadawest.org:team/ismg6mi3ytuao2qw", "Brandon"]], "id": "canadawest.org:game/20170112_caua", "source": "canadawest.org"}